recallio/__init__.py
recallio/client.py
recallio/errors.py
recallio/models.py
recallio-1.2.7.dist-info/METADATA
recallio-1.2.7.dist-info/WHEEL
recallio-1.2.7.dist-info/top_level.txt
recallio-1.2.7.dist-info/RECORD
