Metadata-Version: 2.4
Name: recallio
Version: 1.2.7
Summary: Python client for the Recallio API
Author-email: Recallio Team <support@recallio.com>
Project-URL: Homepage, https://app.recallio.ai
Requires-Python: >=3.8
Requires-Dist: requests>=2.31
